[
  {
    "name": "align_exceeds_input",
    "target_fn": "align_to_usize",
    "type": "behavioral",
    "reason": "Downward alignment must never return a value exceeding the original input",
    "entailed": false,
    "verified": 33,
    "errors": 1,
    "output_tail": "gn_exceeds_input(a: usize, b: usize)\n    |       ------------------------------------------------ at the end of the function body\n...\n657 |         align_to_usize(a, b) > a,\n    |         ^^^^^^^^^^^^^^^^^^^^^^^^ failed this postcondition\n\nerror: aborting due to 1 previous error; 1 warning emitted\n\n"
  },
  {
    "name": "align_to_one_changes_value",
    "target_fn": "align_to_usize",
    "type": "boundary",
    "reason": "Aligning to 1 should be a no-op since every integer is 1-aligned; a changed value would indicate a broken spec",
    "entailed": false,
    "verified": 33,
    "errors": 1,
    "output_tail": "_align_to_one_changes_value(a: usize)\n    |       --------------------------------------------- at the end of the function body\n...\n657 |         align_to_usize(a, 1) != a,\n    |         ^^^^^^^^^^^^^^^^^^^^^^^^^ failed this postcondition\n\nerror: aborting due to 1 previous error; 1 warning emitted\n\n"
  },
  {
    "name": "nonzero_align_stays_nonzero",
    "target_fn": "align_to_usize",
    "type": "behavioral",
    "reason": "A nonzero address aligned down can legitimately become zero (e.g., a=1 b=4096); if the spec claims otherwise it is too strong",
    "entailed": false,
    "verified": 33,
    "errors": 1,
    "output_tail": "_nonzero(a: usize, b: usize)\n    |       -------------------------------------------------------- at the end of the function body\n...\n658 |         align_to_usize(a, b) > 0,\n    |         ^^^^^^^^^^^^^^^^^^^^^^^^ failed this postcondition\n\nerror: aborting due to 1 previous error; 1 warning emitted\n\n"
  },
  {
    "name": "aligned_additive_divisors",
    "target_fn": "aligned",
    "type": "logical",
    "reason": "Alignment to two sizes does not imply alignment to their sum (e.g., 12 is aligned to 4 and 6 but not to 10)",
    "entailed": false,
    "verified": 33,
    "errors": 1,
    "output_tail": "r: nat, s1: nat, s2: nat)\n    |       --------------------------------------------------------------- at the end of the function body\n...\n660 |         aligned(addr, s1 + s2),\n    |         ^^^^^^^^^^^^^^^^^^^^^^ failed this postcondition\n\nerror: aborting due to 1 previous error; 1 warning emitted\n\n"
  },
  {
    "name": "align_result_double_aligned",
    "target_fn": "align_to_usize",
    "type": "logical",
    "reason": "Aligning down to b does not guarantee the result is also aligned to 2b (e.g., align_to_usize(5,4)==4 but 4 is not 8-aligned)",
    "entailed": false,
    "verified": 33,
    "errors": 1,
    "output_tail": "----------------------------------------- at the end of the function body\n...\n658 |         aligned(align_to_usize(a, b) as nat, (b * 2) as nat),\n    |         ^^^^^^^^^^^^^^^^^^^^^^^^^^^^^^^^^^^^^^^^^^^^^^^^^^^^ failed this postcondition\n\nerror: aborting due to 1 previous error; 1 warning emitted\n\n"
  }
]