[
  {
    "name": "align_exceeds_input",
    "target_fn": "align_to_usize",
    "type": "behavioral",
    "code": "proof fn phi_1_align_exceeds_input(a: usize, b: usize)\n    requires\n        b > 0,\n    ensures\n        align_to_usize(a, b) > a,\n{\n}",
    "reason": "Aligning down should never produce a value greater than the original input"
  },
  {
    "name": "align_result_not_multiple",
    "target_fn": "align_to_usize",
    "type": "behavioral",
    "code": "proof fn phi_2_align_result_not_multiple(a: usize, b: usize)\n    requires\n        b > 0,\n    ensures\n        align_to_usize(a, b) % b != 0,\n{\n}",
    "reason": "The result of downward alignment must be a multiple of the alignment boundary"
  },
  {
    "name": "aligned_idempotent_fails",
    "target_fn": "align_to_usize",
    "type": "logical",
    "code": "proof fn phi_3_aligned_idempotent_fails(a: usize, b: usize)\n    requires\n        b > 0,\n        aligned(a as nat, b as nat),\n    ensures\n        align_to_usize(a, b) != a,\n{\n}",
    "reason": "If the input is already aligned, align_to_usize must be the identity\u2014returning a different value is a spec inconsistency"
  },
  {
    "name": "zero_not_aligned",
    "target_fn": "aligned",
    "type": "boundary",
    "code": "proof fn phi_4_zero_not_aligned(size: nat)\n    requires\n        size > 0,\n    ensures\n        !aligned(0, size),\n{\n}",
    "reason": "Zero is trivially divisible by any positive number, so aligned(0, size) must be true"
  },
  {
    "name": "align_noop_when_unaligned",
    "target_fn": "align_to_usize",
    "type": "boundary",
    "code": "proof fn phi_5_align_noop_when_unaligned(a: usize, b: usize)\n    requires\n        b > 0,\n        a % b != 0,\n    ensures\n        align_to_usize(a, b) == a,\n{\n}",
    "reason": "When the input is not aligned, align_to_usize must adjust it downward\u2014returning it unchanged means alignment is broken"
  }
]